CONTRIBUTING.rst
HISTORY.rst
LICENSE
MANIFEST.in
README.rst
setup.cfg
setup.py
cycle_calendar_generator/__init__.py
cycle_calendar_generator/__main__.py
cycle_calendar_generator/cycle_calendar_generator.py
cycle_calendar_generator.egg-info/PKG-INFO
cycle_calendar_generator.egg-info/SOURCES.txt
cycle_calendar_generator.egg-info/dependency_links.txt
cycle_calendar_generator.egg-info/entry_points.txt
cycle_calendar_generator.egg-info/not-zip-safe
cycle_calendar_generator.egg-info/requires.txt
cycle_calendar_generator.egg-info/top_level.txt
docs/Makefile
docs/conf.py
docs/contributing.rst
docs/history.rst
docs/index.rst
docs/make.bat
docs/readme.rst
tests/__init__.py
tests/test_cycle_calendar_generator.py
tests/test_integration.py
tests/integration_test/expected/Teacher Two.ics
tests/integration_test/expected/Test Teacher.ics
tests/integration_test/testing_files/Teacher Two.xlsx
tests/integration_test/testing_files/Test Teacher.xlsx
tests/integration_test/testing_files/schedule_setup.xlsx