Metadata-Version: 1.1
Name: cycle-calendar-generator
Version: 0.2.0
Summary: Generates iCal files for class schedules for schools using an N-day cycle
Home-page: https://github.com/ROldford/cycle_calendar_generator
Author: Ryan William Maynard Oldford
Author-email: ryan.oldford@gmail.com
License: GNU General Public License v3
Keywords: cycle_calendar_generator
Platform: UNKNOWN
Classifier: Development Status :: 2 - Pre-Alpha
Classifier: Intended Audience :: Developers
Classifier: License :: OSI Approved :: GNU General Public License v3 (GPLv3)
Classifier: Natural Language :: English
Classifier: Programming Language :: Python :: 3.5
Classifier: Programming Language :: Python :: 3.6
Classifier: Programming Language :: Python :: 3.7
